rapidpro4rapidsms/__init__.py
rapidpro4rapidsms/forms.py
rapidpro4rapidsms/models.py
rapidpro4rapidsms/outgoing.py
rapidpro4rapidsms/urls.py
rapidpro4rapidsms/views.py
rapidpro_for_rapidsms-1.0.3.dist-info/DESCRIPTION.rst
rapidpro_for_rapidsms-1.0.3.dist-info/METADATA
rapidpro_for_rapidsms-1.0.3.dist-info/RECORD
rapidpro_for_rapidsms-1.0.3.dist-info/WHEEL
rapidpro_for_rapidsms-1.0.3.dist-info/metadata.json
rapidpro_for_rapidsms-1.0.3.dist-info/top_level.txt
tests/__init__.py
tests/base.py
tests/test_forms.py
tests/test_outgoing.py
tests/test_views.py
