Metadata-Version: 2.0
Name: rapidpro-for-rapidsms
Version: 1.0.3
Summary: A RapidPro backend for RapidSMS.
Home-page: https://github.com/system7ltd/rapidpro-for-rapidsms
Author: Tomasz J. Kotarba
Author-email: tomasz@kotarba.net
License: BSD
Keywords: rapidsms rapidpro sms django textit
Platform: UNKNOWN
Classifier: Development Status :: 5 - Production/Stable
Classifier: Intended Audience :: Developers
Classifier: Intended Audience :: System Administrators
Classifier: Intended Audience :: Telecommunications Industry
Classifier: Intended Audience :: Information Technology
Classifier: Topic :: Communications
Classifier: Topic :: Internet
Classifier: Topic :: Software Development :: Libraries
Classifier: Topic :: Software Development :: Libraries :: Application Frameworks
Classifier: Framework :: Django
Classifier: Operating System :: OS Independent
Classifier: License :: OSI Approved :: BSD License
Classifier: Programming Language :: Python :: 2
Classifier: Programming Language :: Python :: 2.6
Classifier: Programming Language :: Python :: 2.7
Classifier: Programming Language :: Python :: 3
Classifier: Programming Language :: Python :: 3.3
Classifier: Programming Language :: Python :: 3.4
Classifier: Programming Language :: Python :: 3.5
Requires-Dist: django (<1.9,>=1.7)
Requires-Dist: rapidpro-python (>=2.1.6)
Requires-Dist: rapidsms (>=0.18.0)
Provides-Extra: development
Requires-Dist: mock; extra == 'development'
